README.md
README.rst
setup.cfg
setup.py
DateJS/__init__.py
DateJS.egg-info/PKG-INFO
DateJS.egg-info/SOURCES.txt
DateJS.egg-info/dependency_links.txt
DateJS.egg-info/entry_points.txt
DateJS.egg-info/requires.txt
DateJS.egg-info/top_level.txt