Metadata-Version: 1.1
Name: DateJS
Version: 0.5
Summary: Python Library that converts Javascript Date objects to Python Datetime objects
Home-page: https://github.com/rithik/DateJS
Author: Rithik Yelisetty
Author-email: rithik@gmail.com
License: MIT
Platform: UNKNOWN
Classifier: License :: OSI Approved :: MIT License
Classifier: Programming Language :: Python :: 3
